wfs/__init__.py
wfs/cli.py
wfs/convert_tcase.py
wfs/fgen.py
wfs/mproxy.py
wfs/proxy.py
wfs/pages/__init__.py
wfs/pages/action_step.py
wfs/pages/app_page.py
wfs/pages/base_page.py
wfs/pages/object_repo_page.py
wfs/utils/__init__.py
wfs/utils/action_test_item.py
wfs/utils/assertions.py
wfs/utils/common.py
wfs/utils/confapp.py
wfs/utils/desired_actions.py
wfs/utils/parseexcel.py
wfs/utils/process_input.py
wfs/utils/response.py
wfs/utils/ui_conditions.py
wfs-1.4.7.dist-info/LICENSE
wfs-1.4.7.dist-info/METADATA
wfs-1.4.7.dist-info/WHEEL
wfs-1.4.7.dist-info/entry_points.txt
wfs-1.4.7.dist-info/top_level.txt
wfs-1.4.7.dist-info/RECORD
